{
    "category": [
        {
            "id": "1",
            "name": "ÁO POLO",
            "gender": ["male", "female", "child"],
            "filename": "ao-polo.jpg"
        },
        {
            "id": "2",
            "name": "ÁO THUN",
            "gender": ["male", "female", "child"],
            "filename": "ao-thun.jpg"
        },
        {
            "id": "3",
            "name": "ÁO KHOÁC",
            "gender": ["male", "female", "child"],
            "filename": "ao-khoac.jpg"
        },
        {
            "id": "4",
            "name": "QUẦN BÒ",
            "gender": ["male", "female"],
            "filename": "quan-bo.jpg"
        },
        {
            "id": "5",
            "name": "ĐỒ BỘ",
            "gender": ["male", "child"],
            "filename": "do-bo.jpg"
        },
        {
            "id": "6",
            "name": "CHÂN VÁY",
            "gender": ["female", "child"],
            "filename": "chan-vay.jpg"
        },
        {
            "id": "7",
            "name": "QUẦN ÂU",
            "gender": ["female", "male"],
            "filename": "quan-au.jpg"
        },
        {
            "id": "8",
            "name": "VÁY ĐẦM",
            "gender": ["female", "child"],
            "filename": "vay-dam.jpg"
        },
        {
            "id": "9",
            "name": "ÁO SƠ MI",
            "gender": ["female", "male"],
            "filename": "ao-somi.jpg"
        },
        {
            "id": "10",
            "name": "QUẦN ĐÙI",
            "gender": ["female", "male", "child"],
            "filename": "quan-dui.jpg"
        },
        {
            "id": "11",
            "name": "ĐỒ LÓT",
            "gender": ["female", "male"],
            "filename": "do-lot.jpg"
        },
        {
            "id": "12",
            "name": "PHỤ KIỆN",
            "gender": ["female", "male"],
            "filename": "phu-kien.jpg"
        }
    ]
}